LICENSE
MANIFEST.in
README.md
setup.py
chalk/__init__.py
chalk/log.py
chalk/tests.py
chalk/utils.py
chalk/contrib/__init__.py
chalk/contrib/django.py
pychalk.egg-info/PKG-INFO
pychalk.egg-info/SOURCES.txt
pychalk.egg-info/dependency_links.txt
pychalk.egg-info/requires.txt
pychalk.egg-info/top_level.txt