Metadata-Version: 1.1
Name: pychalk
Version: 1.0.2
Summary: Color printing in python
Home-page: https://github.com/anthonyalmarza/chalk
Author: Anthony Almarza
Author-email: anthony@reeliolabs.com
License: UNKNOWN
Download-URL: https://github.com/anthonyalmarza/chalk/tarball/1.0.2
Keywords: print,color,chalk,logging
Platform: UNKNOWN
Classifier: Development Status :: 5 - Production/Stable
Classifier: Intended Audience :: Developers
Classifier: License :: OSI Approved :: MIT License
Classifier: Operating System :: POSIX
Classifier: Programming Language :: Python
Classifier: Topic :: Internet :: WWW/HTTP
